{"name":"capitalizr","tagline":"A command line program to capitalize/upcase words in a file. First letter of any words are capitalized.","body":"**capitalizr** - It's a utility that lets you change the case *(lowercase to\r\nuppercase the letter of the words)* words in a file, leaving the words which\r\nhave 3 or less letters. The file looks pretty if it has all words in\r\ncapitalcase in it.\r\n\r\n##why not sed?##\r\n * Because capitalizr is easy to use\r\n * sed doesn't takes input from stdin, it just works on piping.\r\n\r\n##How to Install##\r\nThe one and only requirement is Python, if you are on any variant of UNIX \r\n(e.g. Linux, \\*BSD, Mac etc) then you have a good luck, else [download][4] it.\r\nThe simplest installation (for UNIX) is [download][3]/clone the archive, extract\r\nit `cd` to it and run the setup:\r\n\r\n    $ python setup.py install\r\n\r\nRefer to [INSTALL][1] file for more instruction related to installation.\r\n\r\n##Usages##\r\nAfter following the instructions in [INSTALL][1] file, you should be able\r\nto type `capitalizr` in terminal. Type capitalizr followed by the filename\r\nand the output will be on the screen:\r\n\r\n    $ capitalizr inputfile.txt\r\n\r\n\r\nPipe input to it\r\n\r\n    cat inputfile.txt | capitalizr -\r\n\r\nInput from **stdin**\r\n\r\n    the quick brown fox jumps over the lazy dog\r\n    ^D\r\n    the Quick Brown fox Jumps Over the Lazy dog\r\n\r\nYou can write the output into file by passing `-o` followed by output filename\r\n\r\n    capitalizr inputfile.txt -o outputfile.txt\r\n\r\nAnd the output will be on a file named outputfile.txt\r\n\r\n\r\n##Bugs##\r\nBugs and suggestions should be reported at: https://github.com/santosh/capitalizr/issues\r\n\r\n  [1]: https://github.com/santosh/capitalizr/blob/master/INSTALL.md\r\n  [3]: https://github.com/santosh/capitalizr/archive/master.zip\r\n  [4]: http://www.python.org/download/\r\n","google":"Update from README.md, Remove ToDo and Contributors section","note":"Don't delete this file! It's used internally to help with page regeneration."}